{"0000146":{"originTitle":"Fried Egg and Bread Pklatter","isTags":["Fried Eggs","Toast","Baked Beans"],"originUrl":"https://www.pexels.com/photo/103124","license":"Public Domain","descriptiveTags":["breakfast","dairy","fried"],"containsTags":["beans","bread","eggs","Cheese","coffee","butter"],"id":"0000146","licenseUrl":"https://creativecommons.org/publicdomain/","title":"Fried Eggs, Toast and baked beans Breakfast with coffee"}
,"0000189":{"title":"Cheese Plate with accoutrements","originTitle":"Flat Lay Photography of Baked Foods","isTags":["Cheese Plate","Walnuts","Tortilla Chips","Pretzels","Crackers","Grapes","Honey"],"originUrl":"https://www.pexels.com/photo/302457","license":"Public Domain","descriptiveTags":["appetizer","Dessert","Vegetarian","Dairy"],"containsTags":["cheese","high angle shot","jam","Fruit","rosemary","acorn","nuts","chips","salt"],"id":"0000189","licenseUrl":"https://creativecommons.org/publicdomain/"}
,"0000879":{"containsTags":["Spinach"],"id":"0000879","licenseUrl":"https://creativecommons.org/publicdomain/","title":"Mixed Greens Salad with pomegranate and sprouts","originTitle":"Close Up Photography of Bowl Filled With Spice Seasonings","isTags":["Salad","Mixed Greens","pomegranate","pumpkin seeds","sprouts"],"originUrl":"https://www.pexels.com/photo/628777","license":"Public Domain","descriptiveTags":["Asian","Vegetarian","Vegetables"]}
,"0000358":{"isTags":["Fried Egg","Radishes","Tomatoes","Potatoes"],"originUrl":"https://www.pexels.com/photo/22420","license":"Public Domain","descriptiveTags":["breakfast","vegetarian"],"containsTags":["eggs","vegetables"],"id":"0000358","licenseUrl":"https://creativecommons.org/publicdomain/","title":"Fried Egg breakfast with radishes, tomatoes and potatoes","originTitle":"Egg With Vegetable Dish"}
,"0000378":{"isTags":["Asparagus","Lettuce","Tomatoes","Halloumi Burger"],"originUrl":"https://www.pexels.com/photo/416594","license":"Public Domain","descriptiveTags":["Vegetables","vegetarian"],"containsTags":["bread","burger","vegetables","bun","Halloumi","Cheese"],"id":"0000378","licenseUrl":"https://creativecommons.org/publicdomain/","title":"Halloumi Burger With Asparagus, Lettuce and Tomatoes","originTitle":"Burger With Asparagus"}
}